resoto_plugins/__init__.py
resoto_plugins-2.2.0.dist-info/WHEEL
resoto_plugins-2.2.0.dist-info/METADATA
resoto_plugins-2.2.0.dist-info/RECORD
